grafi/agents/react_agent.py
grafi/assistants/assistant.py
grafi/assistants/assistant_base.py
grafi/common/containers/container.py
grafi/common/decorators/llm_function.py
grafi/common/decorators/record_base.py
grafi/common/decorators/record_decorators.py
grafi/common/event_stores/__init__.py
grafi/common/event_stores/event_store.py
grafi/common/event_stores/event_store_in_memory.py
grafi/common/event_stores/event_store_postgres.py
grafi/common/events/component_base.py
grafi/common/events/component_events.py
grafi/common/events/event.py
grafi/common/events/event_graph.py
grafi/common/events/topic_events/consume_from_topic_event.py
grafi/common/events/topic_events/publish_to_topic_event.py
grafi/common/events/topic_events/topic_event.py
grafi/common/exceptions/__init__.py
grafi/common/exceptions/base.py
grafi/common/exceptions/duplicate_node_error.py
grafi/common/exceptions/event_exceptions.py
grafi/common/exceptions/tool_exceptions.py
grafi/common/exceptions/workflow_exceptions.py
grafi/common/instrumentations/tracing.py
grafi/common/models/async_result.py
grafi/common/models/base_builder.py
grafi/common/models/default_id.py
grafi/common/models/event_id.py
grafi/common/models/function_spec.py
grafi/common/models/invoke_context.py
grafi/common/models/mcp_connections.py
grafi/common/models/message.py
grafi/nodes/node.py
grafi/nodes/node_base.py
grafi/tools/command.py
grafi/tools/tool.py
grafi/tools/tool_factory.py
grafi/tools/function_calls/function_call_command.py
grafi/tools/function_calls/function_call_tool.py
grafi/tools/function_calls/impl/agent_calling_tool.py
grafi/tools/function_calls/impl/duckduckgo_tool.py
grafi/tools/function_calls/impl/google_search_tool.py
grafi/tools/function_calls/impl/mcp_tool.py
grafi/tools/function_calls/impl/synthetic_tool.py
grafi/tools/function_calls/impl/tavily_tool.py
grafi/tools/functions/function_tool.py
grafi/tools/functions/impl/mcp_function_tool.py
grafi/tools/llms/llm.py
grafi/tools/llms/llm_command.py
grafi-0.0.34.dist-info/METADATA
grafi-0.0.34.dist-info/WHEEL
grafi-0.0.34.dist-info/licenses/LICENSE
grafi-0.0.34.dist-info/RECORD
