Metadata-Version: 2.4
Name: grafi
Version: 0.0.34
Summary: Grafi - a flexible, event-driven framework that enables the creation of domain-specific AI agents through composable agentic workflows.
Author-email: Craig Li <craig@binome.dev>
License: Mozilla Public License Version 2.0
License-File: LICENSE
Requires-Python: >=3.11
Requires-Dist: anyio>=4.9.0
Requires-Dist: arize-otel>=0.11.0
Requires-Dist: arize-phoenix-otel>=0.14.0
Requires-Dist: cloudpickle>=3.1.1
Requires-Dist: docstring-parser>=0.16
Requires-Dist: loguru>=0.7.3
Requires-Dist: openai>=2.14.0
Requires-Dist: openinference-instrumentation-openai>=0.1.41
Requires-Dist: pydantic>=2.12.5
